<?xml version="1.0" encoding="utf-8"?>
<flashData>
<dataCollection name="feature" id="0"><dataItemLocked name="id" value="anim_partition_rwd" /><dataItemLocked name="type" value="button" /><dataItem name="xpos" value="100" id="0" /></dataCollection><dataCollection name="text" id="1"><dataItemLocked name="id" value="walltext" /><dataItemLocked name="type" value="button" /><dataItem name="title" value="Ground Floor Wall 1" id="1" /><dataItem name="subtitle" value="Animals" id="2" /><dataItem name="blurb" value="Lorem ipsum dolor sit amet, consectetur adipisicing elit, sed do eiusmod tempor incididunt ut labore et dolore magna aliqua. Ut enim ad minim veniam, quis nostrud exercitation ullamco laboris nisi ut aliquip ex ea commodo consequat. " id="3" /><dataItem name="xpos" value="200" id="4" /></dataCollection><dataCollection name="image" id="2"><dataItem name="artistID" value="1" id="5" /><dataItem name="title" value="Cock Crow" id="6" /><dataItem name="size" value="undefined" id="7" /><dataItem name="genre" value="Animals" id="8" /><dataItem name="medium" value="undefined" id="9" /><dataItem name="url" value="cock_crow.jpg" id="10" /><dataItem name="xpos" value="200" id="11" /></dataCollection><dataCollection name="image" id="3"><dataItem name="artistID" value="1" id="12" /><dataItem name="title" value="Pigs from Orwell's %3Ci%3EAnimal Farm%3C%2Fi%3E" id="13" /><dataItem name="size" value="undefined" id="14" /><dataItem name="genre" value="Animals" id="15" /><dataItem name="medium" value="undefined" id="16" /><dataItem name="url" value="animal_farm.jpg" id="17" /><dataItem name="xpos" value="150" id="18" /></dataCollection><dataCollection name="image" id="4"><dataItem name="artistID" value="1" id="19" /><dataItem name="title" value="Drunken Butterfly" id="20" /><dataItem name="size" value="undefined" id="21" /><dataItem name="genre" value="Animals" id="22" /><dataItem name="medium" value="undefined" id="23" /><dataItem name="url" value="drunken_butterfly.jpg" id="24" /><dataItem name="xpos" value="150" id="25" /></dataCollection><dataCollection name="feature" id="5"><dataItemLocked name="id" value="window" /><dataItemLocked name="type" value="graphic" /><dataItem name="xpos" value="150" id="26" /></dataCollection><dataCollection name="image" id="6"><dataItem name="artistID" value="1" id="27" /><dataItem name="title" value="Showing the mouse the way" id="28" /><dataItem name="size" value="undefined" id="29" /><dataItem name="genre" value="Animals" id="30" /><dataItem name="medium" value="undefined" id="31" /><dataItem name="url" value="showing_the_mouse_the_way.jpg" id="32" /><dataItem name="xpos" value="150" id="33" /></dataCollection><dataCollection name="image" id="7"><dataItem name="artistID" value="1" id="34" /><dataItem name="title" value="A Toast" id="35" /><dataItem name="size" value="undefined" id="36" /><dataItem name="genre" value="Food and drink" id="37" /><dataItem name="medium" value="undefined" id="38" /><dataItem name="url" value="a_toast.jpg" id="39" /><dataItem name="xpos" value="150" id="40" /></dataCollection><dataCollection name="image" id="8"><dataItem name="artistID" value="1" id="41" /><dataItem name="title" value="Cheers!" id="42" /><dataItem name="size" value="undefined" id="43" /><dataItem name="genre" value="Food and Drink" id="44" /><dataItem name="medium" value="undefined" id="45" /><dataItem name="url" value="cheers.jpg" id="46" /><dataItem name="xpos" value="150" id="47" /></dataCollection><dataCollection name="image" id="9"><dataItem name="artistID" value="1" id="48" /><dataItem name="title" value="Food &amp;amp; Wine" id="49" /><dataItem name="size" value="undefined" id="50" /><dataItem name="genre" value="Food and Drink" id="51" /><dataItem name="medium" value="undefined" id="52" /><dataItem name="url" value="food_and_wine.jpg" id="53" /><dataItem name="xpos" value="150" id="54" /></dataCollection><dataCollection name="feature" id="10"><dataItemLocked name="id" value="anim_rear_mid_fwd" /><dataItemLocked name="type" value="button" /><dataItem name="xpos" value="150" id="55" /></dataCollection></flashData>
